LICENSE
naif_earth_itrf93/__init__.py
naif_earth_itrf93/earth_assoc_itrf93.md5
naif_earth_itrf93/earth_assoc_itrf93.tf
naif_earth_itrf93/fetch.py
naif_earth_itrf93/tests/__init__.py
naif_earth_itrf93/tests/test_naif_earth_itrf93.py
naif_earth_itrf93-2007.4.3.1.dist-info/licenses/LICENSE
naif_earth_itrf93-2007.4.3.1.dist-info/METADATA
naif_earth_itrf93-2007.4.3.1.dist-info/WHEEL
naif_earth_itrf93-2007.4.3.1.dist-info/top_level.txt
naif_earth_itrf93-2007.4.3.1.dist-info/RECORD
