Metadata-Version: 2.4
Name: naif_earth_itrf93
Version: 2007.4.3.1
Summary: NAIF Earth Body-fixed Reference Frame/Body Association Kernel for SPICE
Author-email: B612 Asteroid Institute <info@b612foundation.org>
License: MIT License
Requires-Python: >=3.7
License-File: LICENSE
Provides-Extra: tests
Requires-Dist: pytest; extra == "tests"
Requires-Dist: spiceypy; extra == "tests"
Dynamic: license-file
